snakerun/__init__.py
snakerun/cli.py
snakerun-0.0.8.dist-info/licenses/LICENSE
snakerun-0.0.8.dist-info/METADATA
snakerun-0.0.8.dist-info/WHEEL
snakerun-0.0.8.dist-info/entry_points.txt
snakerun-0.0.8.dist-info/top_level.txt
snakerun-0.0.8.dist-info/RECORD
