Metadata-Version: 2.4
Name: snakerun
Version: 0.0.8
Summary: A Python based CLI game for playing classical snake game
Author: Ishan Bhat
Author-email: ishan2003bhat@gmail.com
Keywords: snake game python-cli
Classifier: Development Status :: 4 - Beta
Classifier: Intended Audience :: Developers
Classifier: License :: OSI Approved :: MIT License
Classifier: Operating System :: OS Independent
Classifier: Programming Language :: Python :: 3
Classifier: Programming Language :: Python :: 3.6
Classifier: Programming Language :: Python :: 3.7
Classifier: Programming Language :: Python :: 3.8
Classifier: Programming Language :: Python :: 3.9
Classifier: Programming Language :: Python :: 3.10
Classifier: Programming Language :: Python :: 3.11
Classifier: Programming Language :: Python :: 3.12
Requires-Python: >=3.6
License-File: LICENSE
Requires-Dist: windows-curses; platform_system == "Windows"
Provides-Extra: test
Requires-Dist: pexpect; platform_system != "Windows" and extra == "test"
Requires-Dist: pytest; extra == "test"
Requires-Dist: pytest-cov; extra == "test"
Provides-Extra: dev
Requires-Dist: build; extra == "dev"
Requires-Dist: bump-my-version; extra == "dev"
Requires-Dist: pre-commit; extra == "dev"
Requires-Dist: ruff; extra == "dev"
Requires-Dist: twine; extra == "dev"
Provides-Extra: docs
Requires-Dist: insipid-sphinx-theme; extra == "docs"
Requires-Dist: sphinx; extra == "docs"
Provides-Extra: all
Requires-Dist: pexpect; platform_system != "Windows" and extra == "all"
Requires-Dist: pytest; extra == "all"
Requires-Dist: pytest-cov; extra == "all"
Requires-Dist: build; extra == "all"
Requires-Dist: bump-my-version; extra == "all"
Requires-Dist: pre-commit; extra == "all"
Requires-Dist: ruff; extra == "all"
Requires-Dist: twine; extra == "all"
Requires-Dist: insipid-sphinx-theme; extra == "all"
Requires-Dist: sphinx; extra == "all"
Dynamic: author
Dynamic: author-email
Dynamic: classifier
Dynamic: description
Dynamic: description-content-type
Dynamic: keywords
Dynamic: license-file
Dynamic: provides-extra
Dynamic: requires-dist
Dynamic: requires-python
Dynamic: summary
